grpphati/__about__.py
grpphati/__init__.py
grpphati/backends/__init__.py
grpphati/backends/_phat.py
grpphati/backends/abstract.py
grpphati/backends/eirene.py
grpphati/backends/lophat.py
grpphati/backends/persuit.py
grpphati/columns/__init__.py
grpphati/columns/abstract.py
grpphati/columns/directed_triangle.py
grpphati/columns/double_edge.py
grpphati/columns/edge.py
grpphati/columns/eyeglasses.py
grpphati/columns/long_square.py
grpphati/columns/node.py
grpphati/filtrations/__init__.py
grpphati/filtrations/abstract.py
grpphati/filtrations/shortest_path.py
grpphati/filtrations/truncated.py
grpphati/homologies/__init__.py
grpphati/homologies/abstract.py
grpphati/homologies/directed_flag.py
grpphati/homologies/path_homology.py
grpphati/homologies/tuples.py
grpphati/optimisations/__init__.py
grpphati/optimisations/appendages.py
grpphati/optimisations/check_empty.py
grpphati/optimisations/components.py
grpphati/optimisations/composite.py
grpphati/optimisations/wedge.py
grpphati/pipelines/__init__.py
grpphati/pipelines/grounded.py
grpphati/pipelines/standard.py
grpphati/results/__init__.py
grpphati/results/result.py
grpphati/sparsifiers/__init__.py
grpphati/sparsifiers/abstract.py
grpphati/sparsifiers/generator.py
grpphati/sparsifiers/list.py
grpphati/truncations/__init__.py
grpphati/utils/__init__.py
grpphati/utils/graph.py
grpphati-0.4.1.dist-info/METADATA
grpphati-0.4.1.dist-info/WHEEL
grpphati-0.4.1.dist-info/licenses/LICENSE
grpphati-0.4.1.dist-info/RECORD
