Metadata-Version: 2.1
Name: grpphati
Version: 0.4.1
Summary: PHAT implementation of the grounded pipeline and, in particular, GrPPH
Project-URL: Documentation, https://github.com/tomchaplin/grpphati#readme
Project-URL: Issues, https://github.com/tomchaplin/grpphati/issues
Project-URL: Source, https://github.com/tomchaplin/grpphati
Author-email: Thomas Chaplin <tomrchaplin@gmail.com>
License-Expression: MIT
License-File: LICENSE
Classifier: Development Status :: 3 - Alpha
Classifier: Intended Audience :: Science/Research
Classifier: Programming Language :: Python
Classifier: Programming Language :: Python :: 3.7
Classifier: Programming Language :: Python :: 3.8
Classifier: Programming Language :: Python :: 3.9
Classifier: Programming Language :: Python :: 3.10
Classifier: Programming Language :: Python :: 3.11
Classifier: Programming Language :: Python :: Implementation :: CPython
Classifier: Programming Language :: Python :: Implementation :: PyPy
Classifier: Topic :: Scientific/Engineering :: Mathematics
Requires-Python: >=3.7
Requires-Dist: joblib~=1.2.0
Requires-Dist: lophat==0.9.2
Requires-Dist: networkx~=2.8.8
Requires-Dist: numpy~=1.24.1
Provides-Extra: eirene
Requires-Dist: julia~=0.6.0; extra == 'eirene'
Provides-Extra: persuit
Requires-Dist: persuit==0.1.0; extra == 'persuit'
